{
  "table": {
    "home_main_navBtNames": [
      {
        "name": "金融",
        "logo": "static/images/logos/search.png",
        "clickLogo": "static/images/logos/search.png",
        "isClick": true
      },
      {
        "name": "房地产",
        "logo": "static/images/logos/search.png",
        "clickLogo": "static/images/logos/search.png",
        "isClick": false
      },
      {
        "name": "IT互联网",
        "logo": "static/images/logos/search.png",
        "clickLogo": "static/images/logos/search.png",
        "isClick": false
      },
      {
        "name": "消费品",
        "logo": "static/images/logos/search.png",
        "clickLogo": "static/images/logos/search.png",
        "isClick": false
      },
      {
        "name": "汽车制造",
        "logo": "static/images/logos/search.png",
        "clickLogo": "static/images/logos/search.png",
        "isClick": false
      },
      {
        "name": "其它",
        "logo": "static/images/logos/search.png",
        "clickLogo": "static/images/logos/search.png",
        "isClick": false
      }
    ],
    "home_thead": [
      {
        "entryName": "项目名称",
        "BulletinTitle": "公告标题",
        "Price": "价格",
        "state": "状态",
        "date": "日期"
      }
    ],
    "home_tbody": {
      "Finance": [
        {
          "entryName": "日照银行股份有限公司",
          "BulletinTitle": "深圳贝特尔机器有限最新公告...",
          "Price": "3000万",
          "state": "进行中",
          "isStating": true,
          "date": "2018-6-1"
        },
        {
          "entryName": "日照银行股份有限公司",
          "BulletinTitle": "深圳贝特尔机器有限最新公告...",
          "Price": "3000万",
          "state": "进行中",
          "isStating": true,
          "date": "2018-6-1"
        },
        {
          "entryName": "日照银行股份有限公司",
          "BulletinTitle": "深圳贝特尔机器有限最新公告...",
          "Price": "3000万",
          "state": "进行中",
          "isStating": true,
          "date": "2018-6-1"
        },
        {
          "entryName": "日照银行股份有限公司",
          "BulletinTitle": "深圳贝特尔机器有限最新公告...",
          "Price": "3000万",
          "state": "进行中",
          "isStating": true,
          "date": "2018-6-1"
        },
        {
          "entryName": "日照银行股份有限公司",
          "BulletinTitle": "深圳贝特尔机器有限最新公告...",
          "Price": "3000万",
          "state": "已结束",
          "isStating": false,
          "date": "2018-6-1"
        },
        {
          "entryName": "日照银行股份有限公司",
          "BulletinTitle": "深圳贝特尔机器有限最新公告...",
          "Price": "3000万",
          "state": "已结束",
          "isStating": false,
          "date": "2018-6-1"
        },
        {
          "entryName": "日照银行股份有限公司",
          "BulletinTitle": "深圳贝特尔机器有限最新公告...",
          "Price": "3000万",
          "state": "已结束",
          "isStating": false,
          "date": "2018-6-1"
        },
        {
          "entryName": "日照银行股份有限公司",
          "BulletinTitle": "深圳贝特尔机器有限最新公告...",
          "Price": "3000万",
          "state": "进行中",
          "isStating": true,
          "date": "2018-6-1"
        }
      ],
      "estate": [
        {
          "entryName": "estate",
          "BulletinTitle": "深圳贝特尔机器有限最新公告...",
          "Price": "3000万",
          "state": "进行中",
          "isStating": true,
          "date": "2018-6-1"
        },
        {
          "entryName": "日照银行股份有限公司",
          "BulletinTitle": "深圳贝特尔机器有限最新公告...",
          "Price": "3000万",
          "state": "进行中",
          "isStating": true,
          "date": "2018-6-1"
        },
        {
          "entryName": "日照银行股份有限公司",
          "BulletinTitle": "深圳贝特尔机器有限最新公告...",
          "Price": "3000万",
          "state": "进行中",
          "isStating": true,
          "date": "2018-6-1"
        },
        {
          "entryName": "日照银行股份有限公司",
          "BulletinTitle": "深圳贝特尔机器有限最新公告...",
          "Price": "3000万",
          "state": "进行中",
          "isStating": true,
          "date": "2018-6-1"
        },
        {
          "entryName": "日照银行股份有限公司",
          "BulletinTitle": "深圳贝特尔机器有限最新公告...",
          "Price": "3000万",
          "state": "已结束",
          "isStating": false,
          "date": "2018-6-1"
        },
        {
          "entryName": "日照银行股份有限公司",
          "BulletinTitle": "深圳贝特尔机器有限最新公告...",
          "Price": "3000万",
          "state": "已结束",
          "isStating": false,
          "date": "2018-6-1"
        },
        {
          "entryName": "日照银行股份有限公司",
          "BulletinTitle": "深圳贝特尔机器有限最新公告...",
          "Price": "3000万",
          "state": "已结束",
          "isStating": false,
          "date": "2018-6-1"
        },
        {
          "entryName": "日照银行股份有限公司",
          "BulletinTitle": "深圳贝特尔机器有限最新公告...",
          "Price": "3000万",
          "state": "进行中",
          "isStating": true,
          "date": "2018-6-1"
        }
      ],
      "IT": [
        {
          "entryName": "IT",
          "BulletinTitle": "深圳贝特尔机器有限最新公告...",
          "Price": "3000万",
          "state": "进行中",
          "isStating": true,
          "date": "2018-6-1"
        },
        {
          "entryName": "日照银行股份有限公司",
          "BulletinTitle": "深圳贝特尔机器有限最新公告...",
          "Price": "3000万",
          "state": "进行中",
          "isStating": true,
          "date": "2018-6-1"
        },
        {
          "entryName": "日照银行股份有限公司",
          "BulletinTitle": "深圳贝特尔机器有限最新公告...",
          "Price": "3000万",
          "state": "进行中",
          "isStating": true,
          "date": "2018-6-1"
        },
        {
          "entryName": "日照银行股份有限公司",
          "BulletinTitle": "深圳贝特尔机器有限最新公告...",
          "Price": "3000万",
          "state": "进行中",
          "isStating": true,
          "date": "2018-6-1"
        },
        {
          "entryName": "日照银行股份有限公司",
          "BulletinTitle": "深圳贝特尔机器有限最新公告...",
          "Price": "3000万",
          "state": "已结束",
          "isStating": false,
          "date": "2018-6-1"
        },
        {
          "entryName": "日照银行股份有限公司",
          "BulletinTitle": "深圳贝特尔机器有限最新公告...",
          "Price": "3000万",
          "state": "已结束",
          "isStating": false,
          "date": "2018-6-1"
        },
        {
          "entryName": "日照银行股份有限公司",
          "BulletinTitle": "深圳贝特尔机器有限最新公告...",
          "Price": "3000万",
          "state": "已结束",
          "isStating": false,
          "date": "2018-6-1"
        },
        {
          "entryName": "日照银行股份有限公司",
          "BulletinTitle": "深圳贝特尔机器有限最新公告...",
          "Price": "3000万",
          "state": "进行中",
          "isStating": true,
          "date": "2018-6-1"
        }
      ],
      "goods": [
        {
          "entryName": "goods",
          "BulletinTitle": "深圳贝特尔机器有限最新公告...",
          "Price": "3000万",
          "state": "进行中",
          "isStating": true,
          "date": "2018-6-1"
        },
        {
          "entryName": "日照银行股份有限公司",
          "BulletinTitle": "深圳贝特尔机器有限最新公告...",
          "Price": "3000万",
          "state": "进行中",
          "isStating": true,
          "date": "2018-6-1"
        },
        {
          "entryName": "日照银行股份有限公司",
          "BulletinTitle": "深圳贝特尔机器有限最新公告...",
          "Price": "3000万",
          "state": "进行中",
          "isStating": true,
          "date": "2018-6-1"
        },
        {
          "entryName": "日照银行股份有限公司",
          "BulletinTitle": "深圳贝特尔机器有限最新公告...",
          "Price": "3000万",
          "state": "进行中",
          "isStating": true,
          "date": "2018-6-1"
        },
        {
          "entryName": "日照银行股份有限公司",
          "BulletinTitle": "深圳贝特尔机器有限最新公告...",
          "Price": "3000万",
          "state": "已结束",
          "isStating": false,
          "date": "2018-6-1"
        },
        {
          "entryName": "日照银行股份有限公司",
          "BulletinTitle": "深圳贝特尔机器有限最新公告...",
          "Price": "3000万",
          "state": "已结束",
          "isStating": false,
          "date": "2018-6-1"
        },
        {
          "entryName": "日照银行股份有限公司",
          "BulletinTitle": "深圳贝特尔机器有限最新公告...",
          "Price": "3000万",
          "state": "已结束",
          "isStating": false,
          "date": "2018-6-1"
        },
        {
          "entryName": "日照银行股份有限公司",
          "BulletinTitle": "深圳贝特尔机器有限最新公告...",
          "Price": "3000万",
          "state": "进行中",
          "isStating": true,
          "date": "2018-6-1"
        }
      ],
      "car": [
        {
          "entryName": "car",
          "BulletinTitle": "深圳贝特尔机器有限最新公告...",
          "Price": "3000万",
          "state": "进行中",
          "isStating": true,
          "date": "2018-6-1"
        },
        {
          "entryName": "日照银行股份有限公司",
          "BulletinTitle": "深圳贝特尔机器有限最新公告...",
          "Price": "3000万",
          "state": "进行中",
          "isStating": true,
          "date": "2018-6-1"
        },
        {
          "entryName": "日照银行股份有限公司",
          "BulletinTitle": "深圳贝特尔机器有限最新公告...",
          "Price": "3000万",
          "state": "进行中",
          "isStating": true,
          "date": "2018-6-1"
        },
        {
          "entryName": "日照银行股份有限公司",
          "BulletinTitle": "深圳贝特尔机器有限最新公告...",
          "Price": "3000万",
          "state": "进行中",
          "isStating": true,
          "date": "2018-6-1"
        },
        {
          "entryName": "日照银行股份有限公司",
          "BulletinTitle": "深圳贝特尔机器有限最新公告...",
          "Price": "3000万",
          "state": "已结束",
          "isStating": false,
          "date": "2018-6-1"
        },
        {
          "entryName": "日照银行股份有限公司",
          "BulletinTitle": "深圳贝特尔机器有限最新公告...",
          "Price": "3000万",
          "state": "已结束",
          "isStating": false,
          "date": "2018-6-1"
        },
        {
          "entryName": "日照银行股份有限公司",
          "BulletinTitle": "深圳贝特尔机器有限最新公告...",
          "Price": "3000万",
          "state": "已结束",
          "isStating": false,
          "date": "2018-6-1"
        },
        {
          "entryName": "日照银行股份有限公司",
          "BulletinTitle": "深圳贝特尔机器有限最新公告...",
          "Price": "3000万",
          "state": "进行中",
          "isStating": true,
          "date": "2018-6-1"
        }
      ],
      "other": [
        {
          "entryName": "other",
          "BulletinTitle": "深圳贝特尔机器有限最新公告...",
          "Price": "3000万",
          "state": "进行中",
          "isStating": true,
          "date": "2018-6-1"
        },
        {
          "entryName": "日照银行股份有限公司",
          "BulletinTitle": "深圳贝特尔机器有限最新公告...",
          "Price": "3000万",
          "state": "进行中",
          "isStating": true,
          "date": "2018-6-1"
        },
        {
          "entryName": "日照银行股份有限公司",
          "BulletinTitle": "深圳贝特尔机器有限最新公告...",
          "Price": "3000万",
          "state": "进行中",
          "isStating": true,
          "date": "2018-6-1"
        },
        {
          "entryName": "日照银行股份有限公司",
          "BulletinTitle": "深圳贝特尔机器有限最新公告...",
          "Price": "3000万",
          "state": "进行中",
          "isStating": true,
          "date": "2018-6-1"
        },
        {
          "entryName": "日照银行股份有限公司",
          "BulletinTitle": "深圳贝特尔机器有限最新公告...",
          "Price": "3000万",
          "state": "已结束",
          "isStating": false,
          "date": "2018-6-1"
        },
        {
          "entryName": "日照银行股份有限公司",
          "BulletinTitle": "深圳贝特尔机器有限最新公告...",
          "Price": "3000万",
          "state": "已结束",
          "isStating": false,
          "date": "2018-6-1"
        },
        {
          "entryName": "日照银行股份有限公司",
          "BulletinTitle": "深圳贝特尔机器有限最新公告...",
          "Price": "3000万",
          "state": "已结束",
          "isStating": false,
          "date": "2018-6-1"
        },
        {
          "entryName": "日照银行股份有限公司",
          "BulletinTitle": "深圳贝特尔机器有限最新公告...",
          "Price": "3000万",
          "state": "进行中",
          "isStating": true,
          "date": "2018-6-1"
        }
      ]
    }
  }
}